npdtools/__init__.py
npdtools/helpers.py
npdtools/settings.py
npdtools/token_manager.py
npdtools/errors/FNSError.py
npdtools/errors/__init__.py
npdtools/modules/__init__.py
npdtools/modules/base.py
npdtools/modules/income.py
npdtools/modules/invoice.py
npdtools/types/__init__.py
npdtools/types/entity.py
npdtools/types/income.py
npdtools/types/invoice.py
npdtools/types/service.py
npdtools_fx-1.0.1.dist-info/LICENSE
npdtools_fx-1.0.1.dist-info/METADATA
npdtools_fx-1.0.1.dist-info/WHEEL
npdtools_fx-1.0.1.dist-info/top_level.txt
npdtools_fx-1.0.1.dist-info/RECORD
